allcasts/__init__.py
allcasts/allcasts.py
allcasts/itunes_API.py
allcasts-0.2.0.dist-info/LICENSE
allcasts-0.2.0.dist-info/METADATA
allcasts-0.2.0.dist-info/WHEEL
allcasts-0.2.0.dist-info/entry_points.txt
allcasts-0.2.0.dist-info/top_level.txt
allcasts-0.2.0.dist-info/RECORD
