Metadata-Version: 2.1
Name: allcasts
Version: 0.2.0
Summary: A simple command line tool to download all podcasts from a given RSS feed
Home-page: https://github.com/illegalbyte/allcasts
Author: Lewis Gentle
License: MIT
Platform: UNKNOWN
Classifier: Development Status :: 3 - Alpha
Classifier: Intended Audience :: Developers
Classifier: Topic :: Utilities
Classifier: License :: OSI Approved :: MIT License
Classifier: Programming Language :: Python :: 3
Classifier: Programming Language :: Python :: 3.8
Classifier: Programming Language :: Python :: 3.9
License-File: LICENSE
Requires-Dist: PyInputPlus
Requires-Dist: wget
Requires-Dist: xmltodict
Requires-Dist: colorama
Requires-Dist: argparse
